methodk8s/__init__.py
methodk8s/core/__init__.py
methodk8s/core/datetime_utils.py
methodk8s/core/pydantic_utilities.py
methodk8s/core/serialization.py
methodk8s/py.typed
methodk8s/resources/__init__.py
methodk8s/resources/common/__init__.py
methodk8s/resources/common/auth_types.py
methodk8s/resources/common/namespace_info.py
methodk8s/resources/common/node_info.py
methodk8s/resources/common/pod_info.py
methodk8s/resources/common/protocol_types.py
methodk8s/resources/common/service_info.py
methodk8s/resources/ingress/__init__.py
methodk8s/resources/ingress/gateway_info.py
methodk8s/resources/ingress/http_route.py
methodk8s/resources/ingress/ingress.py
methodk8s/resources/ingress/ingress_report.py
methodk8s/resources/ingress/load_balancer.py
methodk8s/resources/ingress/route_info.py
methodk8s/resources/node/__init__.py
methodk8s/resources/node/address_info.py
methodk8s/resources/node/node.py
methodk8s/resources/node/node_report.py
methodk8s/resources/node/state_types.py
methodk8s/resources/pod/__init__.py
methodk8s/resources/pod/container_info.py
methodk8s/resources/pod/container_port_info.py
methodk8s/resources/pod/pod.py
methodk8s/resources/pod/pod_report.py
methodk8s/resources/pod/security_context_info.py
methodk8s/resources/pod/status_info.py
methodk8s/resources/pod/status_types.py
methodk8s/resources/service/__init__.py
methodk8s/resources/service/service.py
methodk8s/resources/service/service_report.py
methodk8s-0.0.12.dist-info/METADATA
methodk8s-0.0.12.dist-info/WHEEL
methodk8s-0.0.12.dist-info/RECORD
